chronumental/__init__.py
chronumental/__main__.py
chronumental/_version.py
chronumental/helpers.py
chronumental/input_mod.py
chronumental/models.py
chronumental-0.0.65.dist-info/LICENSE
chronumental-0.0.65.dist-info/METADATA
chronumental-0.0.65.dist-info/WHEEL
chronumental-0.0.65.dist-info/entry_points.txt
chronumental-0.0.65.dist-info/top_level.txt
chronumental-0.0.65.dist-info/RECORD
